gsv/__init__.py
gsv/_version.py
gsv/exceptions.py
gsv/retriever.py
gsv/variables.md
gsv/area/__init__.py
gsv/area/area_selector.py
gsv/area/rectangular_area_selector.py
gsv/area/utils.py
gsv/decoder/__init__.py
gsv/decoder/attribute_decoder.py
gsv/decoder/grid_decoder.py
gsv/decoder/gsv_decoder.py
gsv/decoder/level_decoder.py
gsv/decoder/message_decoder.py
gsv/decoder/time_decoder.py
gsv/derived/__init__.py
gsv/derived/derived.py
gsv/derived/derived_variables.yaml
gsv/dqc/__init__.py
gsv/dqc/data_available_checker.py
gsv/dqc/dqc_wrapper.py
gsv/dqc/physical_plausibility_checker.py
gsv/dqc/spatial_completeness_checker.py
gsv/dqc/spatial_consistency_checker.py
gsv/dqc/standard_compliance_checker.py
gsv/dqc/profiles/config/bounded.md
gsv/dqc/profiles/config/bounded.yaml
gsv/dqc/profiles/config/grid_mapping.yaml
gsv/dqc/profiles/config/variables.yaml
gsv/dqc/profiles/develop/icon/o2d_daily_healpix_high.yaml
gsv/dqc/profiles/develop/icon/o3d_2_daily_healpix_high.yaml
gsv/dqc/profiles/develop/icon/o3d_daily_healpix_high.yaml
gsv/dqc/profiles/develop/icon/pl_hourly_healpix_high.yaml
gsv/dqc/profiles/develop/icon/sfc_hourly_healpix_high.yaml
gsv/dqc/profiles/develop/ifs-fesom/hl_hourly_healpix_high.yaml
gsv/dqc/profiles/develop/ifs-fesom/hl_hourly_healpix_standard.yaml
gsv/dqc/profiles/develop/ifs-fesom/o2d_daily_healpix_high.yaml
gsv/dqc/profiles/develop/ifs-fesom/o2d_daily_healpix_standard.yaml
gsv/dqc/profiles/develop/ifs-fesom/o3d_2_daily_healpix_high.yaml
gsv/dqc/profiles/develop/ifs-fesom/o3d_2_daily_healpix_standard.yaml
gsv/dqc/profiles/develop/ifs-fesom/o3d_daily_healpix_high.yaml
gsv/dqc/profiles/develop/ifs-fesom/o3d_daily_healpix_standard.yaml
gsv/dqc/profiles/develop/ifs-fesom/pl_hourly_healpix_high.yaml
gsv/dqc/profiles/develop/ifs-fesom/pl_hourly_healpix_standard.yaml
gsv/dqc/profiles/develop/ifs-fesom/sfc_daily_healpix_high.yaml
gsv/dqc/profiles/develop/ifs-fesom/sfc_daily_healpix_standard.yaml
gsv/dqc/profiles/develop/ifs-fesom/sfc_hourly_healpix_high.yaml
gsv_interface-2.13.1.dist-info/METADATA
gsv_interface-2.13.1.dist-info/WHEEL
gsv_interface-2.13.1.dist-info/entry_points.txt
gsv_interface-2.13.1.dist-info/licenses/LICENSE.txt
gsv_interface-2.13.1.dist-info/RECORD
