Metadata-Version: 2.4
Name: gsv-interface
Version: 2.13.1
Summary: Generic State Vector Interface for Destination Earth data.
Author-email: Iker Gonzalez-Yeregi <iker.gonzalez@bsc.es>
License-Expression: Apache-2.0
License-File: LICENSE.txt
Keywords: Climate,ClimateDT,Data,Destination Earth,GSV,Generic State Vector
Classifier: Development Status :: 4 - Beta
Classifier: Intended Audience :: Developers
Classifier: Intended Audience :: End Users/Desktop
Classifier: Intended Audience :: Science/Research
Classifier: Natural Language :: English
Classifier: Operating System :: MacOS
Classifier: Operating System :: Microsoft
Classifier: Operating System :: Unix
Classifier: Programming Language :: Python
Classifier: Programming Language :: Python :: 3
Classifier: Programming Language :: Python :: 3 :: Only
Classifier: Programming Language :: Python :: 3.8
Classifier: Programming Language :: Python :: 3.9
Classifier: Programming Language :: Python :: 3.10
Classifier: Programming Language :: Python :: 3.11
Classifier: Topic :: Scientific/Engineering
Classifier: Topic :: Software Development
Classifier: Topic :: Utilities
Requires-Python: >=3.8
Requires-Dist: cdo
Requires-Dist: cfgrib
Requires-Dist: dask
Requires-Dist: eccodes
Requires-Dist: healpy
Requires-Dist: jinja2
Requires-Dist: netcdf4
Requires-Dist: numpy
Requires-Dist: packaging
Requires-Dist: polytope-client
Requires-Dist: pyfdb==0.1.2
Requires-Dist: pyyaml
Requires-Dist: smmregrid>=0.1.1
Requires-Dist: sparse
Requires-Dist: xarray
Provides-Extra: all
Requires-Dist: gsv[check,doc,test]; extra == 'all'
Provides-Extra: check
Requires-Dist: black<24,>=23; extra == 'check'
Requires-Dist: isort[colors]<6; extra == 'check'
Provides-Extra: doc
Requires-Dist: docutils>=0.18; extra == 'doc'
Requires-Dist: myst-parser>=0.18; extra == 'doc'
Requires-Dist: numpydoc>=1.1; extra == 'doc'
Requires-Dist: pydata-sphinx-theme>=0.13; extra == 'doc'
Requires-Dist: sphinx-design>=0.3; extra == 'doc'
Requires-Dist: sphinx>=5; extra == 'doc'
Provides-Extra: test
Requires-Dist: pytest-cov>=3; extra == 'test'
